<?xml version="1.0" encoding="UTF-8"?>
<objects serializationModel="Studio.02.02.00">
	<object class="AudioFile" id="{3cc69752-3cac-4ea0-857c-adbe6c7e8d37}">
		<property name="assetPath">
			<value>Instrument/Song 1/S1_Guitar.wav</value>
		</property>
		<property name="isStreaming">
			<value>true</value>
		</property>
		<property name="frequencyInKHz">
			<value>44.0999985</value>
		</property>
		<property name="channelCount">
			<value>2</value>
		</property>
		<property name="length">
			<value>57.488775510204079</value>
		</property>
		<relationship name="masterAssetFolder">
			<destination>{84c45c5e-a8a0-4e2c-908e-0514c03af974}</destination>
		</relationship>
	</object>
</objects>
