{"inkVersion":21,"root":[["\n",{"->":"Cine_1"},["done",{"#f":5,"#n":"g-0"}],null],"done",{"Cine_1":["#","^speaker: Haley ","/#","#","^portrait: harvey_chill_annoyed ","/#","#","^portrait: haley_speaking_normal-alt1","/#","^Get up you big grouch, we need you!","\n","#","^speaker: Harvey ","/#","#","^portrait: haley_chill_huh ","/#","#","^portrait: harvey_speaking_annoyed","/#","^Ughhh. What do you want, Haley?","\n","#","^speaker: Haley ","/#","#","^portrait: harvey_chill_annoyed ","/#","#","^portrait: haley_speaking_bummed","/#","^Please don't tell me you forgot about the gig today. You promised you would start helping us.","\n","#","^speaker: Harvey ","/#","#","^portrait: haley_chill_concerned ","/#","#","^portrait: harvey_speaking_normal","/#","^Oh crap. I'll be there in a second, I gotta get dressed.","\n","#","^speaker: Haley ","/#","#","^portrait: harvey_chill_normal ","/#","#","^portrait: haley_speaking_nervous","/#","^Well hurry up, it starts in 20 minutes.","\n","#","^speaker: Harvey ","/#","#","^portrait: haley_chill_normal ","/#","#","^portrait: harvey_speaking_normal-alt","/#","^Ok, ok. I get it. I'll be down in a minute.","\n","end",{"#f":1}],"global decl":["ev",false,{"VAR=":"Has_Haley_Gift"},false,{"VAR=":"Given_Haley_Gift"},false,{"VAR=":"Has_Ace_Gift"},false,{"VAR=":"Given_Ace_Gift"},false,{"VAR=":"Has_MJ_Gift"},false,{"VAR=":"Given_MJ_Gift"},false,{"VAR=":"Has_Kurt_Gift"},false,{"VAR=":"Given_Kurt_Gift"},"/ev","end",null],"#f":1}],"listDefs":{}}